metadata_service/__init__.py
metadata_service/application/__init__.py
metadata_service/application/config.py
metadata_service/application/metadata_service.py
metadata_service/domain/__init__.py
metadata_service/domain/models.py
metadata_service/domain/repositories.py
metadata_service/domain/services.py
metadata_service/infrastructure/__init__.py
metadata_service/infrastructure/database.py
metadata_service/infrastructure/encryption.py
metadata_service/infrastructure/header_parser.py
tests/__init__.py
tests/test_encryption.py
tests/test_header_parser.py
tests/test_metadata_service.py
marfyl_metadata_service-0.3.0.dist-info/METADATA
marfyl_metadata_service-0.3.0.dist-info/WHEEL
marfyl_metadata_service-0.3.0.dist-info/top_level.txt
marfyl_metadata_service-0.3.0.dist-info/RECORD
